pyllo_kickstart/__init__.py
pyllo_kickstart/main.py
pyllo_kickstart/dockableplugin/__init__.py
pyllo_kickstart/dockableplugin/cookiecutter.json
pyllo_kickstart/dockableplugin/{{cookiecutter.project_name}}/__init__.py
pyllo_kickstart/dockableplugin/{{cookiecutter.project_name}}/setup.py
pyllo_kickstart/dockableplugin/{{cookiecutter.project_name}}/startup.py
pyllo_kickstart/dockableplugin/{{cookiecutter.project_name}}/{{cookiecutter.project_name}}/__init__.py
pyllo_kickstart/dockableplugin/{{cookiecutter.project_name}}/{{cookiecutter.project_name}}/api.py
pyllo_kickstart/dockableplugin/{{cookiecutter.project_name}}/{{cookiecutter.project_name}}/confpage.py
pyllo_kickstart/dockableplugin/{{cookiecutter.project_name}}/{{cookiecutter.project_name}}/plugin.py
pyllo_kickstart/dockableplugin/{{cookiecutter.project_name}}/{{cookiecutter.project_name}}/widgets/__init__.py
pyllo_kickstart/dockableplugin/{{cookiecutter.project_name}}/{{cookiecutter.project_name}}/widgets/mainwidget.py
pyllo_kickstart/plugin/__init__.py
pyllo_kickstart/plugin/cookiecutter.json
pyllo_kickstart/plugin/{{cookiecutter.project_name}}/__init__.py
pyllo_kickstart/plugin/{{cookiecutter.project_name}}/setup.py
pyllo_kickstart/plugin/{{cookiecutter.project_name}}/startup.py
pyllo_kickstart/plugin/{{cookiecutter.project_name}}/{{cookiecutter.project_name}}/__init__.py
pyllo_kickstart/plugin/{{cookiecutter.project_name}}/{{cookiecutter.project_name}}/api.py
pyllo_kickstart/plugin/{{cookiecutter.project_name}}/{{cookiecutter.project_name}}/confpage.py
pyllo_kickstart/plugin/{{cookiecutter.project_name}}/{{cookiecutter.project_name}}/container.py
pyllo_kickstart/plugin/{{cookiecutter.project_name}}/{{cookiecutter.project_name}}/plugin.py
pyllo_kickstart-1.0.3.dist-info/LICENSE.txt
pyllo_kickstart-1.0.3.dist-info/METADATA
pyllo_kickstart-1.0.3.dist-info/WHEEL
pyllo_kickstart-1.0.3.dist-info/entry_points.txt
pyllo_kickstart-1.0.3.dist-info/top_level.txt
pyllo_kickstart-1.0.3.dist-info/RECORD
