Metadata-Version: 2.1
Name: pyllo-kickstart
Version: 1.0.3
Summary: Pyllo plugin generator
Home-page: 
Author: Shanghai Connet Information Technology Company Ltd.
Author-email: tech_support@shconnet.com.cn
License: UNKNOWN
Keywords: pyllo plugin template generator
Platform: UNKNOWN
Classifier: Intended Audience :: Developers
Classifier: Programming Language :: Python
Classifier: Programming Language :: Python :: 3.6
Classifier: Programming Language :: Python :: 3.7
Classifier: Programming Language :: Python :: 3.8
Classifier: Programming Language :: Python :: 3.9
Classifier: Programming Language :: Python :: Implementation :: CPython
Classifier: Topic :: Software Development :: Interpreters
License-File: LICENSE.txt
Requires-Dist: pyllo (>=1.0.0.dev0)
Requires-Dist: rich (==13.3.5)
Requires-Dist: cookiecutter (==2.1.1)
Requires-Dist: applaunchservices (==0.3.0)
